EnglishLanguageAPI/__init__.py
EnglishLanguageAPI/API/__init__.py
EnglishLanguageAPI-1.0.1.dist-info/METADATA
EnglishLanguageAPI-1.0.1.dist-info/WHEEL
EnglishLanguageAPI-1.0.1.dist-info/top_level.txt
EnglishLanguageAPI-1.0.1.dist-info/RECORD
