Metadata-Version: 2.1
Name: EnglishLanguageAPI
Version: 1.0.1
Summary: A CLI tool for looking up the meanings of things.
Author-email: Hunter Dale <hunter@guyyatsu.me>
Project-URL: Homepage, https://github.com/guyyatsu/EnglishLanguageAPI
Project-URL: Issues, https://github.com/guyyatsu/EnglishLanguageAPI/issues
Classifier: Programming Language :: Python :: 3
Classifier: License :: OSI Approved :: MIT License
Classifier: Operating System :: OS Independent
Requires-Python: >=3.11
Requires-Dist: bs4
Requires-Dist: requests
